jacktrade/__init__.py
jacktrade/benchmark.py
jacktrade/buffers.py
jacktrade/cache.py
jacktrade/collections.py
jacktrade/files.py
jacktrade/multicore.py
jacktrade/pickler.py
jacktrade/sysenv.py
jacktrade-0.13.0.dist-info/licenses/LICENSE.md
jacktrade-0.13.0.dist-info/METADATA
jacktrade-0.13.0.dist-info/WHEEL
jacktrade-0.13.0.dist-info/entry_points.txt
jacktrade-0.13.0.dist-info/top_level.txt
jacktrade-0.13.0.dist-info/RECORD
