Metadata-Version: 2.4
Name: jacktrade
Version: 0.13.0
Summary: A collection of commonly used Python utilities.
Author-email: Mario Zaja <mzaja0@gmail.com>
License-Expression: MIT
Project-URL: Homepage, https://github.com/mzaja/jacktrade
Project-URL: Bug Tracker, https://github.com/mzaja/jacktrade/issues
Project-URL: Changelog, https://github.com/mzaja/jacktrade/blob/main/HISTORY.md
Keywords: utils,utilities
Classifier: Programming Language :: Python :: 3.10
Classifier: Programming Language :: Python :: 3.11
Classifier: Programming Language :: Python :: 3.12
Classifier: Programming Language :: Python :: 3.13
Classifier: Programming Language :: Python :: 3.14
Classifier: Operating System :: OS Independent
Requires-Python: >=3.10
License-File: LICENSE.md
Dynamic: license-file
